maelstrom/__init__.py
maelstrom/genotype.py
maelstrom/island.py
maelstrom/population.py
maelstrom/selection/parent.py
maelstrom/selection/unique.py
maelstrom_evolution-0.1.0.dist-info/LICENSE
maelstrom_evolution-0.1.0.dist-info/METADATA
maelstrom_evolution-0.1.0.dist-info/WHEEL
maelstrom_evolution-0.1.0.dist-info/RECORD
